odoo8_addon_fetchmail_notify_error_to_sender-8.0.1.0.1-py2.7-nspkg.pth
odoo8_addon_fetchmail_notify_error_to_sender-8.0.1.0.1.dist-info/top_level.txt
odoo8_addon_fetchmail_notify_error_to_sender-8.0.1.0.1.dist-info/WHEEL
odoo8_addon_fetchmail_notify_error_to_sender-8.0.1.0.1.dist-info/RECORD
odoo8_addon_fetchmail_notify_error_to_sender-8.0.1.0.1.dist-info/metadata.json
odoo8_addon_fetchmail_notify_error_to_sender-8.0.1.0.1.dist-info/DESCRIPTION.rst
odoo8_addon_fetchmail_notify_error_to_sender-8.0.1.0.1.dist-info/METADATA
odoo8_addon_fetchmail_notify_error_to_sender-8.0.1.0.1.dist-info/namespace_packages.txt
odoo_addons/fetchmail_notify_error_to_sender/email_template_data.xml
odoo_addons/fetchmail_notify_error_to_sender/__openerp__.py
odoo_addons/fetchmail_notify_error_to_sender/mail_thread.py
odoo_addons/fetchmail_notify_error_to_sender/__init__.py
odoo_addons/fetchmail_notify_error_to_sender/fetchmail.py
odoo_addons/fetchmail_notify_error_to_sender/README.rst
odoo_addons/fetchmail_notify_error_to_sender/fetchmail_view.xml
odoo_addons/fetchmail_notify_error_to_sender/i18n/it.po
odoo_addons/fetchmail_notify_error_to_sender/i18n/es.po
odoo_addons/fetchmail_notify_error_to_sender/i18n/tr.po
odoo_addons/fetchmail_notify_error_to_sender/i18n/sl.po
odoo_addons/fetchmail_notify_error_to_sender/i18n/pt_PT.po
odoo_addons/fetchmail_notify_error_to_sender/i18n/de.po
odoo_addons/fetchmail_notify_error_to_sender/i18n/fr.po
odoo_addons/fetchmail_notify_error_to_sender/i18n/pt_BR.po
odoo_addons/fetchmail_notify_error_to_sender/static/description/icon.png
