Metadata-Version: 2.0
Name: odoo8-addon-fetchmail-notify-error-to-sender
Version: 8.0.1.0.1
Summary: If fetching mails gives error, send an email to sender
Home-page: http://www.agilebg.com
Author: Agile Business Group,Odoo Community Association (OCA)
Author-email: support@odoo-community.org
License: AGPL-3
Platform: UNKNOWN
Requires-Dist: odoo (<9.0a,>=8.0a)
Classifier: Programming Language :: Python :: 2.7
Classifier: Framework :: Odoo
Classifier: License :: OSI Approved :: GNU Affero General Public License v3
